mereja/__init__.py
mereja/constants.py
mereja/main.py
mereja/utils.py
mereja/functions/__init__.py
mereja/functions/forex.py
mereja/functions/jobs.py
mereja/functions/market.py
mereja/functions/news.py
mereja/functions/telebirr.py
mereja/ui/__init__.py
mereja/ui/forex_table_ui.py
mereja/ui/job_view_ui.py
mereja/ui/marketpalce_ui.py
mereja/ui/news_view_ui.py
mereja/ui/transaction_table.py
mereja/ui/widgets/__init__.py
mereja/ui/widgets/header.py
mereja-0.0.8.dist-info/METADATA
mereja-0.0.8.dist-info/WHEEL
mereja-0.0.8.dist-info/entry_points.txt
mereja-0.0.8.dist-info/top_level.txt
mereja-0.0.8.dist-info/RECORD
