Metadata-Version: 2.1
Name: mereja
Version: 0.0.8
Home-page: https://github.com/wizkiye/mereja
Author: Kidus
Author-email: wizkiye@gmail.com
License: MIT
Classifier: Programming Language :: Python :: 3
Classifier: License :: OSI Approved :: MIT License
Classifier: Operating System :: OS Independent
Requires-Python: >=3.8
Requires-Dist: rich
Requires-Dist: textual
Requires-Dist: markdownify
Requires-Dist: qrcode
Requires-Dist: questionary
Requires-Dist: pyEthioJobs
Requires-Dist: pyEthioNews
Requires-Dist: jiji
Requires-Dist: telebirrTxChecker
Requires-Dist: linkify-it-py
